{
  "refreshedAt": "2026-06-17T14:08:48Z",
  "asOf": "2026-06-17",
  "expiry": "2026-06-23",
  "indices": {
    "NIFTY": {
      "spot": {
        "value": 23995.0,
        "unit": "points",
        "change": null,
        "source": "Upstox NIFTY50 PCR analysis page",
        "sourceUrl": "https://upstox.com/fno-discovery/open-interest-analysis/nifty-pcr/",
        "asOf": "2026-06-16",
        "freshness": "SNAPSHOT",
        "bias": "Neutral",
        "note": "Spot shown on Upstox OI page for weekly expiry context."
      },
      "futuresBasis": {
        "value": null,
        "unit": "points",
        "change": null,
        "source": null,
        "sourceUrl": null,
        "asOf": "2026-06-17",
        "freshness": "DNA",
        "bias": "Neutral",
        "note": "Not available from static sources in this run."
      },
      "futuresOi": {
        "value": null,
        "unit": "contracts",
        "change": null,
        "source": null,
        "sourceUrl": null,
        "asOf": "2026-06-17",
        "freshness": "DNA",
        "bias": "Neutral",
        "note": "Not available from static sources in this run."
      },
      "buildup": "Neutral",
      "fiiIndexFutures": {
        "value": null,
        "unit": "contracts",
        "change": null,
        "source": null,
        "sourceUrl": null,
        "asOf": "2026-06-17",
        "freshness": "DNA",
        "bias": "Neutral",
        "note": "Not sourced from approved static pages in this run."
      },
      "pcr": {
        "value": 1.0346,
        "unit": "ratio",
        "change": null,
        "source": "Upstox NIFTY50 PCR analysis page",
        "sourceUrl": "https://upstox.com/fno-discovery/open-interest-analysis/nifty-pcr/",
        "asOf": "2026-06-16",
        "freshness": "SNAPSHOT",
        "bias": "Bullish",
        "note": "PCR > 1 indicates put OI exceeds call OI."
      },
      "maxPain": {
        "value": null,
        "unit": "strike",
        "change": null,
        "source": null,
        "sourceUrl": null,
        "asOf": "2026-06-17",
        "freshness": "DNA",
        "bias": "Neutral",
        "note": "Max pain not stated in available static sources."
      },
      "support": {
        "value": 24000,
        "unit": "strike",
        "change": null,
        "source": "Upstox trade setup article",
        "sourceUrl": "https://upstox.com/news/market-news/trading/trade-setup-for-june-17-can-nifty-50-sustain-above-24-000-on-wednesday/article-195467/",
        "asOf": "2026-06-17",
        "freshness": "SNAPSHOT",
        "bias": "Neutral",
        "note": "Highest put OI stated at 24,000 in article."
      },
      "resistance": {
        "value": 24000,
        "unit": "strike",
        "change": null,
        "source": "Upstox trade setup article",
        "sourceUrl": "https://upstox.com/news/market-news/trading/trade-setup-for-june-17-can-nifty-50-sustain-above-24-000-on-wednesday/article-195467/",
        "asOf": "2026-06-17",
        "freshness": "SNAPSHOT",
        "bias": "Neutral",
        "note": "Highest call OI stated at 24,000 in article."
      },
      "indiaVix": {
        "value": 13.47,
        "unit": "index",
        "change": 0.11,
        "source": "Upstox India VIX index page",
        "sourceUrl": "https://upstox.com/indices/india-vix-share-price/",
        "asOf": "2026-06-17",
        "freshness": "SNAPSHOT",
        "bias": "Bullish",
        "note": "Market-wide implied volatility."
      },
      "fnoVerdict": {
        "verdict": "Neutral",
        "confidence": "Low",
        "rationale": "Futures basis/OI and FII index-futures positioning were not sourced from approved static pages in this run; verdict kept neutral."
      },
      "optionsVerdict": {
        "verdict": "Neutral",
        "confidence": "Low",
        "rationale": "PCR is mildly supportive but max pain and dominant strikes beyond 24,000 were not sourced; verdict kept neutral."
      },
      "combinedVerdict": {
        "verdict": "Neutral",
        "confidence": "Low",
        "rationale": "Insufficient sourced futures+options cues for a high-conviction directional read."
      }
    },
    "SENSEX": {
      "spot": {
        "value": 76826.78,
        "unit": "points",
        "change": null,
        "source": "Upstox SENSEX OI analysis page",
        "sourceUrl": "https://upstox.com/fno-discovery/open-interest-analysis/sensex-oi/",
        "asOf": "2026-06-16",
        "freshness": "SNAPSHOT",
        "bias": "Neutral",
        "note": "Spot shown on Upstox OI page for weekly expiry context."
      },
      "futuresBasis": {
        "value": null,
        "unit": "points",
        "change": null,
        "source": null,
        "sourceUrl": null,
        "asOf": "2026-06-17",
        "freshness": "DNA",
        "bias": "Neutral",
        "note": "Sensex futures basis not available from static sources in this run."
      },
      "futuresOi": {
        "value": null,
        "unit": "contracts",
        "change": null,
        "source": null,
        "sourceUrl": null,
        "asOf": "2026-06-17",
        "freshness": "DNA",
        "bias": "Neutral",
        "note": "Sensex futures OI not available from static sources in this run."
      },
      "buildup": "Neutral",
      "fiiIndexFutures": {
        "value": null,
        "unit": "contracts",
        "change": null,
        "source": null,
        "sourceUrl": null,
        "asOf": "2026-06-17",
        "freshness": "DNA",
        "bias": "Neutral",
        "note": "Not split for Sensex in official statistics."
      },
      "pcr": {
        "value": 1.4388,
        "unit": "ratio",
        "change": null,
        "source": "Upstox SENSEX OI analysis page",
        "sourceUrl": "https://upstox.com/fno-discovery/open-interest-analysis/sensex-oi/",
        "asOf": "2026-06-16",
        "freshness": "SNAPSHOT",
        "bias": "Bullish",
        "note": "Computed as total put OI / total call OI from Upstox totals."
      },
      "maxPain": {
        "value": null,
        "unit": "strike",
        "change": null,
        "source": null,
        "sourceUrl": null,
        "asOf": "2026-06-17",
        "freshness": "DNA",
        "bias": "Neutral",
        "note": "Max pain not available from static sources in this run."
      },
      "support": {
        "value": null,
        "unit": "strike",
        "change": null,
        "source": null,
        "sourceUrl": null,
        "asOf": "2026-06-17",
        "freshness": "DNA",
        "bias": "Neutral",
        "note": "Support strike not sourced in this run."
      },
      "resistance": {
        "value": null,
        "unit": "strike",
        "change": null,
        "source": null,
        "sourceUrl": null,
        "asOf": "2026-06-17",
        "freshness": "DNA",
        "bias": "Neutral",
        "note": "Resistance strike not sourced in this run."
      },
      "indiaVix": {
        "value": 13.47,
        "unit": "index",
        "change": 0.11,
        "source": "Upstox India VIX index page",
        "sourceUrl": "https://upstox.com/indices/india-vix-share-price/",
        "asOf": "2026-06-17",
        "freshness": "SNAPSHOT",
        "bias": "Bullish",
        "note": "Market-wide implied volatility (applied to Sensex too)."
      },
      "fnoVerdict": {
        "verdict": "Neutral",
        "confidence": "Low",
        "rationale": "Futures basis/OI and FII index-futures positioning were not sourced from approved static pages in this run; verdict kept neutral."
      },
      "optionsVerdict": {
        "verdict": "Neutral",
        "confidence": "Low",
        "rationale": "PCR is mildly supportive but max pain and dominant strikes beyond 24,000 were not sourced; verdict kept neutral."
      },
      "combinedVerdict": {
        "verdict": "Neutral",
        "confidence": "Low",
        "rationale": "Insufficient sourced futures+options cues for a high-conviction directional read."
      }
    }
  }
}
